CHANGES.rst
MANIFEST.in
README.rst
buildout.cfg
pyproject.toml
requirements.txt
setup.cfg
setup.py
src/bda/__init__.py
src/bda.cache.egg-info/PKG-INFO
src/bda.cache.egg-info/SOURCES.txt
src/bda.cache.egg-info/dependency_links.txt
src/bda.cache.egg-info/entry_points.txt
src/bda.cache.egg-info/namespace_packages.txt
src/bda.cache.egg-info/not-zip-safe
src/bda.cache.egg-info/requires.txt
src/bda.cache.egg-info/top_level.txt
src/bda/cache/__init__.py
src/bda/cache/configure.zcml
src/bda/cache/fscache.py
src/bda/cache/fscache.txt
src/bda/cache/interfaces.py
src/bda/cache/memcached.py
src/bda/cache/memcached.txt
src/bda/cache/nullcache.py
src/bda/cache/nullcache.txt
src/bda/cache/tests/__init__.py
src/bda/cache/tests/test_cache.py