Metadata-Version: 2.1
Name: bda.cache
Version: 1.3.0
Summary: Simple caching infrastructure.
Home-page: https://svn.plone.org/svn/collective/bda.cache
Author: Robert Niederreiter
Author-email: rnix@squarewave.at
License: GPL: GNU General Public Licence
Keywords: caching memcached fscache zope zca
Platform: UNKNOWN
Classifier: Development Status :: 5 - Production/Stable
Classifier: Environment :: Web Environment
Classifier: Framework :: Zope2
Classifier: License :: OSI Approved :: GNU General Public License (GPL)
Classifier: Operating System :: OS Independent
Classifier: Programming Language :: Python
Classifier: Programming Language :: Python :: 2.7
Classifier: Programming Language :: Python :: 3.6
Classifier: Programming Language :: Python :: 3.7
Classifier: Topic :: Internet :: WWW/HTTP :: Dynamic Content
Provides-Extra: libmc
Provides-Extra: test
Provides-Extra: pylibmc
